odoo9_addon_medical_patient_disease_allergy-9.0.1.0.0-py2.7-nspkg.pth
odoo_addons/medical_patient_disease_allergy/__openerp__.py
odoo_addons/medical_patient_disease_allergy/__init__.py
odoo_addons/medical_patient_disease_allergy/README.rst
odoo_addons/medical_patient_disease_allergy/models/medical_patient.py
odoo_addons/medical_patient_disease_allergy/models/__init__.py
odoo_addons/medical_patient_disease_allergy/models/medical_patient_disease.py
odoo_addons/medical_patient_disease_allergy/views/medical_patient_disease_view.xml
odoo_addons/medical_patient_disease_allergy/views/medical_patient_view.xml
odoo_addons/medical_patient_disease_allergy/data/medical_pathology_code_type.xml
odoo_addons/medical_patient_disease_allergy/tests/test_medical_patient_disease.py
odoo_addons/medical_patient_disease_allergy/tests/__init__.py
odoo_addons/medical_patient_disease_allergy/tests/test_medical_patient.py
odoo_addons/medical_patient_disease_allergy/demo/medical_patient_demo.xml
odoo_addons/medical_patient_disease_allergy/demo/medical_pathology_demo.xml
odoo_addons/medical_patient_disease_allergy/demo/medical_patient_disease_demo.xml
odoo_addons/medical_patient_disease_allergy/static/description/icon.png
odoo9_addon_medical_patient_disease_allergy-9.0.1.0.0.dist-info/top_level.txt
odoo9_addon_medical_patient_disease_allergy-9.0.1.0.0.dist-info/WHEEL
odoo9_addon_medical_patient_disease_allergy-9.0.1.0.0.dist-info/RECORD
odoo9_addon_medical_patient_disease_allergy-9.0.1.0.0.dist-info/metadata.json
odoo9_addon_medical_patient_disease_allergy-9.0.1.0.0.dist-info/DESCRIPTION.rst
odoo9_addon_medical_patient_disease_allergy-9.0.1.0.0.dist-info/METADATA
odoo9_addon_medical_patient_disease_allergy-9.0.1.0.0.dist-info/namespace_packages.txt
